native/wpinet/_init_robotpy_native_wpinet.py
native/wpinet/robotpy-native-wpinet.pc
native/wpinet/include/uv.h
native/wpinet/include/uv/bsd.h
native/wpinet/include/uv/darwin.h
native/wpinet/include/uv/errno.h
native/wpinet/include/uv/linux.h
native/wpinet/include/uv/posix.h
native/wpinet/include/uv/threadpool.h
native/wpinet/include/uv/tree.h
native/wpinet/include/uv/unix.h
native/wpinet/include/uv/version.h
native/wpinet/include/uv/win.h
native/wpinet/include/wpinet/DsClient.h
native/wpinet/include/wpinet/EventLoopRunner.h
native/wpinet/include/wpinet/HttpParser.h
native/wpinet/include/wpinet/HttpServerConnection.h
native/wpinet/include/wpinet/HttpUtil.h
native/wpinet/include/wpinet/HttpWebSocketServerConnection.h
native/wpinet/include/wpinet/MimeTypes.h
native/wpinet/include/wpinet/MulticastServiceAnnouncer.h
native/wpinet/include/wpinet/MulticastServiceResolver.h
native/wpinet/include/wpinet/NetworkAcceptor.h
native/wpinet/include/wpinet/NetworkStream.h
native/wpinet/include/wpinet/ParallelTcpConnector.h
native/wpinet/include/wpinet/PortForwarder.h
native/wpinet/include/wpinet/SocketError.h
native/wpinet/include/wpinet/TCPAcceptor.h
native/wpinet/include/wpinet/TCPConnector.h
native/wpinet/include/wpinet/TCPStream.h
native/wpinet/include/wpinet/UDPClient.h
native/wpinet/include/wpinet/UrlParser.h
native/wpinet/include/wpinet/WebServer.h
native/wpinet/include/wpinet/WebSocket.h
native/wpinet/include/wpinet/WebSocketServer.h
native/wpinet/include/wpinet/WorkerThread.h
native/wpinet/include/wpinet/hostname.h
native/wpinet/include/wpinet/http_parser.h
native/wpinet/include/wpinet/raw_socket_istream.h
native/wpinet/include/wpinet/raw_socket_ostream.h
native/wpinet/include/wpinet/raw_uv_ostream.h
native/wpinet/include/wpinet/uv/Async.h
native/wpinet/include/wpinet/uv/AsyncFunction.h
native/wpinet/include/wpinet/uv/Buffer.h
native/wpinet/include/wpinet/uv/Check.h
native/wpinet/include/wpinet/uv/Error.h
native/wpinet/include/wpinet/uv/FsEvent.h
robotpy_native_wpinet-2025.3.2.dist-info/METADATA
robotpy_native_wpinet-2025.3.2.dist-info/WHEEL
robotpy_native_wpinet-2025.3.2.dist-info/entry_points.txt
robotpy_native_wpinet-2025.3.2.dist-info/RECORD
