Metadata-Version: 2.4
Name: robotpy-native-wpinet
Version: 2025.3.2
Summary: WPILib Networking Library
License-Expression: BSD-3-Clause
Requires-Dist: robotpy-native-wpiutil==2025.3.2
